LICENSE.txt
README.md
Readme.md
pyproject.toml
setup.py
epmwebapi/__init__.py
epmwebapi/_version.py
epmwebapi/advancedevent.py
epmwebapi/aggregatedetails.py
epmwebapi/annotationvaluejson.py
epmwebapi/attributeoperand.py
epmwebapi/authorizationservice.py
epmwebapi/autostarttimer.py
epmwebapi/basicvariable.py
epmwebapi/basicvariablepropertymask.py
epmwebapi/browsedirection.py
epmwebapi/browseitemmodeljson.py
epmwebapi/browsemodeljson.py
epmwebapi/browseresultitemmodeljson.py
epmwebapi/browseresultmodeljson.py
epmwebapi/customtypedefinition.py
epmwebapi/dataobjectattributes.py
epmwebapi/dataobjectsfilter.py
epmwebapi/datasetconfig.py
epmwebapi/datasetpen.py
epmwebapi/datavaluejson.py
epmwebapi/diagnosticmodeljson.py
epmwebapi/domainfilter.py
epmwebapi/downloadtype.py
epmwebapi/elementoperand.py
epmwebapi/epmconnection.py
epmwebapi/epmconnectioncontext.py
epmwebapi/epmdataobject.py
epmwebapi/epmmodelobject.py
epmwebapi/epmnodeids.py
epmwebapi/epmobject.py
epmwebapi/epmproperty.py
epmwebapi/epmsession.py
epmwebapi/epmutils.py
epmwebapi/epmvariable.py
epmwebapi/epmwebapi.py
epmwebapi/eventfiltermodel.py
epmwebapi/exporttype.py
epmwebapi/filtermodel.py
epmwebapi/filteroperand.py
epmwebapi/folder.py
epmwebapi/historyeventmodeljson.py
epmwebapi/historyprocessedmodeljson.py
epmwebapi/historyrawmodeljson.py
epmwebapi/historyresultitemmodeljson.py
epmwebapi/historyresultmodeljson.py
epmwebapi/historyupdatedataitemmodeljson.py
epmwebapi/historyupdatedatamodeljson.py
epmwebapi/historyupdateresultmodeljson.py
epmwebapi/historyupdatetype.py
epmwebapi/itempathandcontinuationpointjson.py
epmwebapi/itempathjson.py
epmwebapi/literaloperand.py
epmwebapi/mimetype.py
epmwebapi/nodeattributes.py
epmwebapi/nodeclassmask.py
epmwebapi/numpyextras.py
epmwebapi/performupdatetype.py
epmwebapi/portalresources.py
epmwebapi/processorresources.py
epmwebapi/queryfiltercontent.py
epmwebapi/queryfilterelement.py
epmwebapi/querymodelfilterJSON.py
epmwebapi/querymodeljson.py
epmwebapi/queryperiod.py
epmwebapi.egg-info/PKG-INFO
epmwebapi.egg-info/SOURCES.txt
epmwebapi.egg-info/dependency_links.txt
epmwebapi.egg-info/requires.txt
epmwebapi.egg-info/top_level.txt
