Metadata-Version: 2.4
Name: epmwebapi
Version: 6.50.38
Home-page: https://github.com/elipsesoftware/epmwebapi
Author: Elipse Software Ltda
License-Expression: GPL-3.0-only
Classifier: Development Status :: 3 - Alpha
Classifier: Intended Audience :: Developers
Classifier: Topic :: Software Development :: Build Tools
Classifier: Programming Language :: Python :: 3.10
Classifier: Programming Language :: Python :: 3.11
Classifier: Programming Language :: Python :: 3.12
Requires-Python: >=3.6, <4
License-File: LICENSE.txt
Requires-Dist: numpy
Requires-Dist: requests
Requires-Dist: python-dateutil
Requires-Dist: pytz
Requires-Dist: pythonnet
Dynamic: author
Dynamic: home-page
Dynamic: license-file
Dynamic: requires-python
